error_narrator/__init__.py
error_narrator/gradio_models.py
error_narrator/narrator.py
error_narrator-0.3.2.dist-info/METADATA
error_narrator-0.3.2.dist-info/WHEEL
error_narrator-0.3.2.dist-info/RECORD
