Metadata-Version: 2.3
Name: error-narrator
Version: 0.3.2
Summary: A Python library to get AI-powered explanations for exceptions using Hugging Face models.
Author: Timur
Author-email: kk7629803@gmail.com
Requires-Python: >=3.7
Classifier: Programming Language :: Python :: 3
Classifier: License :: OSI Approved :: MIT License
Classifier: Operating System :: OS Independent
Requires-Dist: httpx
Requires-Dist: requests
Requires-Dist: rich
Project-URL: Homepage, https://github.com/Zahabsbs
Project-URL: Issues, https://github.com/Zahabsbs/error-narrator/issues
